spacy_coref/__init__.py
spacy_coref/coref_resolver.py
spacy_coref/spacy_component.py
spacy_coref-0.1.1.dist-info/METADATA
spacy_coref-0.1.1.dist-info/WHEEL
spacy_coref-0.1.1.dist-info/entry_points.txt
spacy_coref-0.1.1.dist-info/RECORD
