Metadata-Version: 2.3
Name: spacy-coref
Version: 0.1.1
Summary: Lightweight cross-lingual coreference resolution with spaCy using ONNX Runtime inference of transformer models.
License: MIT
Keywords: coreference,coreference resolution,onnx,onnxruntime,spacy,nlp,natural language processing,transformers,crosslingual,multilingual,huggingface
Author: Tal Almagor
Author-email: almagoric@gmail.com
Requires-Python: >=3.11,<3.13
Classifier: Development Status :: 3 - Alpha
Classifier: License :: OSI Approved :: MIT License
Classifier: Programming Language :: Python :: 3.11
Classifier: Programming Language :: Python :: 3.12
Classifier: Programming Language :: Python :: 3
Classifier: Operating System :: OS Independent
Classifier: Intended Audience :: Science/Research
Classifier: Topic :: Scientific/Engineering :: Artificial Intelligence
Classifier: Topic :: Text Processing :: Linguistic
Requires-Dist: huggingface-hub (>=0.34.3,<0.35.0)
Requires-Dist: onnxruntime (>=1.22.1,<2.0.0)
Requires-Dist: spacy (>=3.8.7,<4.0.0)
Requires-Dist: tokenizers (>=0.21.4,<0.22.0)
